[
  {
    "create": "subprocesses",
    "validator": {
      "$jsonSchema": {
        "bsonType": "object",
        "required": ["name", "process_id", "created_by", "updated_by", "deleted_by", "deleted_at", "created_at", "updated_at", "is_deleted"],
        "properties": {
          "name": { "bsonType": "string" },
          "process_id": { "bsonType": "objectId" },
          "created_by": { "bsonType": "objectId" },
          "updated_by": { "bsonType": ["objectId", "null"]},
          "deleted_by": { "bsonType": ["objectId", "null"]},
          "deleted_at": { "bsonType": ["date", "null"] },
          "created_at": { "bsonType": "date" },
          "updated_at": { "bsonType": "date" },
          "is_deleted": { "bsonType": "bool" }
        }
      }
    }
  },
  {
    "createIndexes": "subprocesses",
    "indexes": [
      { "key": { "name": 1 }, "name": "uniq_name", "unique": true }
    ]
  }
]

